{
  "game_date": "2022-11-09",
  "home": "MIN",
  "visitor": "PHX",
  "home_pts": 117,
  "visitor_pts": 129,
  "home_starters": [
    "Jaden McDaniels",
    "Anthony Edwards",
    "D'Angelo Russell",
    "Rudy Gobert",
    "Karl-Anthony Towns"
  ],
  "visitor_starters": [
    "Mikal Bridges",
    "Devin Booker",
    "Cameron Payne",
    "Deandre Ayton",
    "Torrey Craig"
  ],
  "players": [
    {
      "player_name": "Mikal Bridges",
      "team": "PHX",
      "is_home": false,
      "is_starter": true,
      "mp": 42.3,
      "fg": 12,
      "fga": 20,
      "fg_pct": 0.6,
      "fg3": 2,
      "fg3a": 6,
      "fg3_pct": 0.333,
      "ft": 5,
      "fta": 5,
      "ft_pct": 1.0,
      "orb": 2,
      "drb": 7,
      "trb": 9,
      "ast": 5,
      "stl": 4,
      "blk": 1,
      "tov": 2,
      "pf": 1,
      "pts": 31,
      "plus_minus": 12.0,
      "adv_ts_pct": 0.698,
      "adv_efg_pct": 0.65,
      "adv_orb_pct": 5.7,
      "adv_drb_pct": 23.4,
      "adv_trb_pct": 13.8,
      "adv_ast_pct": 17.0,
      "adv_stl_pct": 4.5,
      "adv_blk_pct": 2.2,
      "adv_tov_pct": 8.3,
      "adv_usg_pct": 23.5,
      "adv_off_rtg": 139.0,
      "adv_def_rtg": 108.0,
      "adv_bpm": 10.9
    },
    {
      "player_name": "Devin Booker",
      "team": "PHX",
      "is_home": false,
      "is_starter": true,
      "mp": 38.2,
      "fg": 12,
      "fga": 23,
      "fg_pct": 0.522,
      "fg3": 5,
      "fg3a": 7,
      "fg3_pct": 0.714,
      "ft": 3,
      "fta": 3,
      "ft_pct": 1.0,
      "orb": 0,
      "drb": 4,
      "trb": 4,
      "ast": 10,
      "stl": 2,
      "blk": 0,
      "tov": 1,
      "pf": 2,
      "pts": 32,
      "plus_minus": 26.0,
      "adv_ts_pct": 0.658,
      "adv_efg_pct": 0.63,
      "adv_orb_pct": 0.0,
      "adv_drb_pct": 14.8,
      "adv_trb_pct": 6.8,
      "adv_ast_pct": 39.4,
      "adv_stl_pct": 2.5,
      "adv_blk_pct": 0.0,
      "adv_tov_pct": 3.9,
      "adv_usg_pct": 27.3,
      "adv_off_rtg": 142.0,
      "adv_def_rtg": 115.0,
      "adv_bpm": 12.5
    },
    {
      "player_name": "Cameron Payne",
      "team": "PHX",
      "is_home": false,
      "is_starter": true,
      "mp": 35.0,
      "fg": 8,
      "fga": 17,
      "fg_pct": 0.471,
      "fg3": 4,
      "fg3a": 9,
      "fg3_pct": 0.444,
      "ft": 3,
      "fta": 3,
      "ft_pct": 1.0,
      "orb": 1,
      "drb": 5,
      "trb": 6,
      "ast": 8,
      "stl": 1,
      "blk": 0,
      "tov": 0,
      "pf": 1,
      "pts": 23,
      "plus_minus": 10.0,
      "adv_ts_pct": 0.628,
      "adv_efg_pct": 0.588,
      "adv_orb_pct": 3.4,
      "adv_drb_pct": 20.2,
      "adv_trb_pct": 11.1,
      "adv_ast_pct": 30.4,
      "adv_stl_pct": 1.3,
      "adv_blk_pct": 0.0,
      "adv_tov_pct": 0.0,
      "adv_usg_pct": 21.5,
      "adv_off_rtg": 147.0,
      "adv_def_rtg": 117.0,
      "adv_bpm": 7.8
    },
    {
      "player_name": "Deandre Ayton",
      "team": "PHX",
      "is_home": false,
      "is_starter": true,
      "mp": 33.0,
      "fg": 4,
      "fga": 10,
      "fg_pct": 0.4,
      "fg3": 0,
      "fg3a": 0,
      "fg3_pct": null,
      "ft": 1,
      "fta": 2,
      "ft_pct": 0.5,
      "orb": 2,
      "drb": 4,
      "trb": 6,
      "ast": 2,
      "stl": 0,
      "blk": 0,
      "tov": 2,
      "pf": 1,
      "pts": 9,
      "plus_minus": 16.0,
      "adv_ts_pct": 0.414,
      "adv_efg_pct": 0.4,
      "adv_orb_pct": 7.3,
      "adv_drb_pct": 17.1,
      "adv_trb_pct": 11.8,
      "adv_ast_pct": 7.1,
      "adv_stl_pct": 0.0,
      "adv_blk_pct": 0.0,
      "adv_tov_pct": 15.5,
      "adv_usg_pct": 16.1,
      "adv_off_rtg": 89.0,
      "adv_def_rtg": 121.0,
      "adv_bpm": -9.9
    },
    {
      "player_name": "Torrey Craig",
      "team": "PHX",
      "is_home": false,
      "is_starter": true,
      "mp": 26.1,
      "fg": 2,
      "fga": 5,
      "fg_pct": 0.4,
      "fg3": 2,
      "fg3a": 3,
      "fg3_pct": 0.667,
      "ft": 0,
      "fta": 0,
      "ft_pct": null,
      "orb": 2,
      "drb": 3,
      "trb": 5,
      "ast": 1,
      "stl": 1,
      "blk": 0,
      "tov": 2,
      "pf": 4,
      "pts": 6,
      "plus_minus": -6.0,
      "adv_ts_pct": 0.6,
      "adv_efg_pct": 0.6,
      "adv_orb_pct": 9.2,
      "adv_drb_pct": 16.3,
      "adv_trb_pct": 12.5,
      "adv_ast_pct": 4.3,
      "adv_stl_pct": 1.8,
      "adv_blk_pct": 0.0,
      "adv_tov_pct": 28.6,
      "adv_usg_pct": 11.0,
      "adv_off_rtg": 101.0,
      "adv_def_rtg": 116.0,
      "adv_bpm": -5.2
    },
    {
      "player_name": "Landry Shamet",
      "team": "PHX",
      "is_home": false,
      "is_starter": false,
      "mp": 18.9,
      "fg": 5,
      "fga": 7,
      "fg_pct": 0.714,
      "fg3": 2,
      "fg3a": 3,
      "fg3_pct": 0.667,
      "ft": 4,
      "fta": 4,
      "ft_pct": 1.0,
      "orb": 0,
      "drb": 0,
      "trb": 0,
      "ast": 1,
      "stl": 0,
      "blk": 0,
      "tov": 3,
      "pf": 2,
      "pts": 16,
      "plus_minus": 8.0,
      "adv_ts_pct": 0.913,
      "adv_efg_pct": 0.857,
      "adv_orb_pct": 0.0,
      "adv_drb_pct": 0.0,
      "adv_trb_pct": 0.0,
      "adv_ast_pct": 7.4,
      "adv_stl_pct": 0.0,
      "adv_blk_pct": 0.0,
      "adv_tov_pct": 25.5,
      "adv_usg_pct": 25.5,
      "adv_off_rtg": 126.0,
      "adv_def_rtg": 123.0,
      "adv_bpm": 1.0
    },
    {
      "player_name": "Damion Lee",
      "team": "PHX",
      "is_home": false,
      "is_starter": false,
      "mp": 15.5,
      "fg": 1,
      "fga": 5,
      "fg_pct": 0.2,
      "fg3": 1,
      "fg3a": 4,
      "fg3_pct": 0.25,
      "ft": 0,
      "fta": 0,
      "ft_pct": null,
      "orb": 0,
      "drb": 0,
      "trb": 0,
      "ast": 1,
      "stl": 0,
      "blk": 0,
      "tov": 1,
      "pf": 1,
      "pts": 3,
      "plus_minus": -14.0,
      "adv_ts_pct": 0.3,
      "adv_efg_pct": 0.3,
      "adv_orb_pct": 0.0,
      "adv_drb_pct": 0.0,
      "adv_trb_pct": 0.0,
      "adv_ast_pct": 7.0,
      "adv_stl_pct": 0.0,
      "adv_blk_pct": 0.0,
      "adv_tov_pct": 16.7,
      "adv_usg_pct": 15.9,
      "adv_off_rtg": 63.0,
      "adv_def_rtg": 123.0,
      "adv_bpm": -14.2
    },
    {
      "player_name": "Dario \u00c5\u00a0ari\u00c4\u0087",
      "team": "PHX",
      "is_home": false,
      "is_starter": false,
      "mp": 12.8,
      "fg": 2,
      "fga": 4,
      "fg_pct": 0.5,
      "fg3": 0,
      "fg3a": 1,
      "fg3_pct": 0.0,
      "ft": 1,
      "fta": 1,
      "ft_pct": 1.0,
      "orb": 2,
      "drb": 0,
      "trb": 2,
      "ast": 2,
      "stl": 0,
      "blk": 0,
      "tov": 0,
      "pf": 3,
      "pts": 5,
      "plus_minus": 6.0,
      "adv_ts_pct": 0.563,
      "adv_efg_pct": 0.5,
      "adv_orb_pct": 18.8,
      "adv_drb_pct": 0.0,
      "adv_trb_pct": 10.2,
      "adv_ast_pct": 19.0,
      "adv_stl_pct": 0.0,
      "adv_blk_pct": 0.0,
      "adv_tov_pct": 0.0,
      "adv_usg_pct": 14.3,
      "adv_off_rtg": 150.0,
      "adv_def_rtg": 123.0,
      "adv_bpm": -1.8
    },
    {
      "player_name": "Jock Landale",
      "team": "PHX",
      "is_home": false,
      "is_starter": false,
      "mp": 12.0,
      "fg": 1,
      "fga": 5,
      "fg_pct": 0.2,
      "fg3": 0,
      "fg3a": 1,
      "fg3_pct": 0.0,
      "ft": 2,
      "fta": 2,
      "ft_pct": 1.0,
      "orb": 1,
      "drb": 3,
      "trb": 4,
      "ast": 1,
      "stl": 1,
      "blk": 1,
      "tov": 0,
      "pf": 5,
      "pts": 4,
      "plus_minus": -2.0,
      "adv_ts_pct": 0.34,
      "adv_efg_pct": 0.2,
      "adv_orb_pct": 10.0,
      "adv_drb_pct": 35.3,
      "adv_trb_pct": 21.6,
      "adv_ast_pct": 9.3,
      "adv_stl_pct": 3.9,
      "adv_blk_pct": 7.8,
      "adv_tov_pct": 0.0,
      "adv_usg_pct": 20.1,
      "adv_off_rtg": 98.0,
      "adv_def_rtg": 103.0,
      "adv_bpm": -8.4
    },
    {
      "player_name": "Josh Okogie",
      "team": "PHX",
      "is_home": false,
      "is_starter": false,
      "mp": 3.2,
      "fg": 0,
      "fga": 1,
      "fg_pct": 0.0,
      "fg3": 0,
      "fg3a": 1,
      "fg3_pct": 0.0,
      "ft": 0,
      "fta": 0,
      "ft_pct": null,
      "orb": 0,
      "drb": 0,
      "trb": 0,
      "ast": 0,
      "stl": 0,
      "blk": 0,
      "tov": 0,
      "pf": 0,
      "pts": 0,
      "plus_minus": 6.0,
      "adv_ts_pct": 0.0,
      "adv_efg_pct": 0.0,
      "adv_orb_pct": 0.0,
      "adv_drb_pct": 0.0,
      "adv_trb_pct": 0.0,
      "adv_ast_pct": 0.0,
      "adv_stl_pct": 0.0,
      "adv_blk_pct": 0.0,
      "adv_tov_pct": 0.0,
      "adv_usg_pct": 12.7,
      "adv_off_rtg": 0.0,
      "adv_def_rtg": 123.0,
      "adv_bpm": -20.8
    },
    {
      "player_name": "Bismack Biyombo",
      "team": "PHX",
      "is_home": false,
      "is_starter": false,
      "mp": 3.0,
      "fg": 0,
      "fga": 0,
      "fg_pct": null,
      "fg3": 0,
      "fg3a": 0,
      "fg3_pct": null,
      "ft": 0,
      "fta": 0,
      "ft_pct": null,
      "orb": 0,
      "drb": 0,
      "trb": 0,
      "ast": 0,
      "stl": 1,
      "blk": 1,
      "tov": 0,
      "pf": 1,
      "pts": 0,
      "plus_minus": -2.0,
      "adv_ts_pct": null,
      "adv_efg_pct": null,
      "adv_orb_pct": 0.0,
      "adv_drb_pct": 0.0,
      "adv_trb_pct": 0.0,
      "adv_ast_pct": 0.0,
      "adv_stl_pct": 15.6,
      "adv_blk_pct": 31.0,
      "adv_tov_pct": null,
      "adv_usg_pct": 0.0,
      "adv_off_rtg": 0.0,
      "adv_def_rtg": 68.0,
      "adv_bpm": 13.9
    },
    {
      "player_name": "Jaden McDaniels",
      "team": "MIN",
      "is_home": true,
      "is_starter": true,
      "mp": 38.1,
      "fg": 10,
      "fga": 14,
      "fg_pct": 0.714,
      "fg3": 2,
      "fg3a": 4,
      "fg3_pct": 0.5,
      "ft": 2,
      "fta": 3,
      "ft_pct": 0.667,
      "orb": 4,
      "drb": 4,
      "trb": 8,
      "ast": 3,
      "stl": 0,
      "blk": 1,
      "tov": 2,
      "pf": 2,
      "pts": 24,
      "plus_minus": 8.0,
      "adv_ts_pct": 0.783,
      "adv_efg_pct": 0.786,
      "adv_orb_pct": 14.8,
      "adv_drb_pct": 12.6,
      "adv_trb_pct": 13.6,
      "adv_ast_pct": 13.3,
      "adv_stl_pct": 0.0,
      "adv_blk_pct": 2.0,
      "adv_tov_pct": 11.5,
      "adv_usg_pct": 19.7,
      "adv_off_rtg": 144.0,
      "adv_def_rtg": 130.0,
      "adv_bpm": 6.2
    },
    {
      "player_name": "Anthony Edwards",
      "team": "MIN",
      "is_home": true,
      "is_starter": true,
      "mp": 34.9,
      "fg": 4,
      "fga": 12,
      "fg_pct": 0.333,
      "fg3": 0,
      "fg3a": 4,
      "fg3_pct": 0.0,
      "ft": 3,
      "fta": 6,
      "ft_pct": 0.5,
      "orb": 0,
      "drb": 3,
      "trb": 3,
      "ast": 6,
      "stl": 2,
      "blk": 0,
      "tov": 3,
      "pf": 5,
      "pts": 11,
      "plus_minus": -2.0,
      "adv_ts_pct": 0.376,
      "adv_efg_pct": 0.333,
      "adv_orb_pct": 0.0,
      "adv_drb_pct": 10.3,
      "adv_trb_pct": 5.6,
      "adv_ast_pct": 23.2,
      "adv_stl_pct": 2.7,
      "adv_blk_pct": 0.0,
      "adv_tov_pct": 17.0,
      "adv_usg_pct": 21.8,
      "adv_off_rtg": 83.0,
      "adv_def_rtg": 126.0,
      "adv_bpm": -8.8
    },
    {
      "player_name": "D'Angelo Russell",
      "team": "MIN",
      "is_home": true,
      "is_starter": true,
      "mp": 33.3,
      "fg": 6,
      "fga": 14,
      "fg_pct": 0.429,
      "fg3": 4,
      "fg3a": 9,
      "fg3_pct": 0.444,
      "ft": 4,
      "fta": 4,
      "ft_pct": 1.0,
      "orb": 1,
      "drb": 1,
      "trb": 2,
      "ast": 6,
      "stl": 0,
      "blk": 0,
      "tov": 3,
      "pf": 2,
      "pts": 20,
      "plus_minus": -5.0,
      "adv_ts_pct": 0.635,
      "adv_efg_pct": 0.571,
      "adv_orb_pct": 4.2,
      "adv_drb_pct": 3.6,
      "adv_trb_pct": 3.9,
      "adv_ast_pct": 26.7,
      "adv_stl_pct": 0.0,
      "adv_blk_pct": 0.0,
      "adv_tov_pct": 16.0,
      "adv_usg_pct": 24.3,
      "adv_off_rtg": 121.0,
      "adv_def_rtg": 134.0,
      "adv_bpm": -0.2
    },
    {
      "player_name": "Rudy Gobert",
      "team": "MIN",
      "is_home": true,
      "is_starter": true,
      "mp": 29.9,
      "fg": 8,
      "fga": 11,
      "fg_pct": 0.727,
      "fg3": 0,
      "fg3a": 0,
      "fg3_pct": null,
      "ft": 9,
      "fta": 11,
      "ft_pct": 0.818,
      "orb": 3,
      "drb": 8,
      "trb": 11,
      "ast": 0,
      "stl": 0,
      "blk": 3,
      "tov": 1,
      "pf": 4,
      "pts": 25,
      "plus_minus": -6.0,
      "adv_ts_pct": 0.789,
      "adv_efg_pct": 0.727,
      "adv_orb_pct": 14.2,
      "adv_drb_pct": 32.1,
      "adv_trb_pct": 23.9,
      "adv_ast_pct": 0.0,
      "adv_stl_pct": 0.0,
      "adv_blk_pct": 7.8,
      "adv_tov_pct": 5.9,
      "adv_usg_pct": 24.3,
      "adv_off_rtg": 156.0,
      "adv_def_rtg": 121.0,
      "adv_bpm": 6.9
    },
    {
      "player_name": "Karl-Anthony Towns",
      "team": "MIN",
      "is_home": true,
      "is_starter": true,
      "mp": 27.7,
      "fg": 3,
      "fga": 7,
      "fg_pct": 0.429,
      "fg3": 1,
      "fg3a": 3,
      "fg3_pct": 0.333,
      "ft": 4,
      "fta": 4,
      "ft_pct": 1.0,
      "orb": 0,
      "drb": 8,
      "trb": 8,
      "ast": 4,
      "stl": 0,
      "blk": 1,
      "tov": 3,
      "pf": 4,
      "pts": 11,
      "plus_minus": 4.0,
      "adv_ts_pct": 0.628,
      "adv_efg_pct": 0.5,
      "adv_orb_pct": 0.0,
      "adv_drb_pct": 34.7,
      "adv_trb_pct": 18.8,
      "adv_ast_pct": 19.4,
      "adv_stl_pct": 0.0,
      "adv_blk_pct": 2.8,
      "adv_tov_pct": 25.5,
      "adv_usg_pct": 18.4,
      "adv_off_rtg": 108.0,
      "adv_def_rtg": 124.0,
      "adv_bpm": -2.1
    },
    {
      "player_name": "Jaylen Nowell",
      "team": "MIN",
      "is_home": true,
      "is_starter": false,
      "mp": 22.7,
      "fg": 5,
      "fga": 8,
      "fg_pct": 0.625,
      "fg3": 2,
      "fg3a": 4,
      "fg3_pct": 0.5,
      "ft": 2,
      "fta": 2,
      "ft_pct": 1.0,
      "orb": 0,
      "drb": 2,
      "trb": 2,
      "ast": 3,
      "stl": 0,
      "blk": 0,
      "tov": 7,
      "pf": 3,
      "pts": 14,
      "plus_minus": -11.0,
      "adv_ts_pct": 0.788,
      "adv_efg_pct": 0.75,
      "adv_orb_pct": 0.0,
      "adv_drb_pct": 10.6,
      "adv_trb_pct": 5.7,
      "adv_ast_pct": 20.9,
      "adv_stl_pct": 0.0,
      "adv_blk_pct": 0.0,
      "adv_tov_pct": 44.1,
      "adv_usg_pct": 30.3,
      "adv_off_rtg": 85.0,
      "adv_def_rtg": 132.0,
      "adv_bpm": -8.3
    },
    {
      "player_name": "Kyle Anderson",
      "team": "MIN",
      "is_home": true,
      "is_starter": false,
      "mp": 22.1,
      "fg": 3,
      "fga": 4,
      "fg_pct": 0.75,
      "fg3": 0,
      "fg3a": 1,
      "fg3_pct": 0.0,
      "ft": 2,
      "fta": 2,
      "ft_pct": 1.0,
      "orb": 0,
      "drb": 0,
      "trb": 0,
      "ast": 4,
      "stl": 0,
      "blk": 1,
      "tov": 0,
      "pf": 0,
      "pts": 8,
      "plus_minus": -17.0,
      "adv_ts_pct": 0.82,
      "adv_efg_pct": 0.75,
      "adv_orb_pct": 0.0,
      "adv_drb_pct": 0.0,
      "adv_trb_pct": 0.0,
      "adv_ast_pct": 25.2,
      "adv_stl_pct": 0.0,
      "adv_blk_pct": 3.5,
      "adv_tov_pct": 0.0,
      "adv_usg_pct": 9.5,
      "adv_off_rtg": 182.0,
      "adv_def_rtg": 132.0,
      "adv_bpm": 7.0
    },
    {
      "player_name": "Taurean Prince",
      "team": "MIN",
      "is_home": true,
      "is_starter": false,
      "mp": 19.1,
      "fg": 2,
      "fga": 6,
      "fg_pct": 0.333,
      "fg3": 0,
      "fg3a": 1,
      "fg3_pct": 0.0,
      "ft": 0,
      "fta": 0,
      "ft_pct": null,
      "orb": 0,
      "drb": 1,
      "trb": 1,
      "ast": 0,
      "stl": 0,
      "blk": 0,
      "tov": 0,
      "pf": 1,
      "pts": 4,
      "plus_minus": -22.0,
      "adv_ts_pct": 0.333,
      "adv_efg_pct": 0.333,
      "adv_orb_pct": 0.0,
      "adv_drb_pct": 6.3,
      "adv_trb_pct": 3.4,
      "adv_ast_pct": 0.0,
      "adv_stl_pct": 0.0,
      "adv_blk_pct": 0.0,
      "adv_tov_pct": 0.0,
      "adv_usg_pct": 13.6,
      "adv_off_rtg": 71.0,
      "adv_def_rtg": 133.0,
      "adv_bpm": -12.3
    },
    {
      "player_name": "Jordan McLaughlin",
      "team": "MIN",
      "is_home": true,
      "is_starter": false,
      "mp": 7.0,
      "fg": 0,
      "fga": 1,
      "fg_pct": 0.0,
      "fg3": 0,
      "fg3a": 0,
      "fg3_pct": null,
      "ft": 0,
      "fta": 0,
      "ft_pct": null,
      "orb": 0,
      "drb": 1,
      "trb": 1,
      "ast": 0,
      "stl": 0,
      "blk": 0,
      "tov": 0,
      "pf": 0,
      "pts": 0,
      "plus_minus": -6.0,
      "adv_ts_pct": 0.0,
      "adv_efg_pct": 0.0,
      "adv_orb_pct": 0.0,
      "adv_drb_pct": 17.2,
      "adv_trb_pct": 9.3,
      "adv_ast_pct": 0.0,
      "adv_stl_pct": 0.0,
      "adv_blk_pct": 0.0,
      "adv_tov_pct": 0.0,
      "adv_usg_pct": 6.2,
      "adv_off_rtg": 0.0,
      "adv_def_rtg": 130.0,
      "adv_bpm": -13.5
    },
    {
      "player_name": "Nathan Knight",
      "team": "MIN",
      "is_home": true,
      "is_starter": false,
      "mp": 5.3,
      "fg": 0,
      "fga": 1,
      "fg_pct": 0.0,
      "fg3": 0,
      "fg3a": 1,
      "fg3_pct": 0.0,
      "ft": 0,
      "fta": 0,
      "ft_pct": null,
      "orb": 0,
      "drb": 2,
      "trb": 2,
      "ast": 0,
      "stl": 2,
      "blk": 0,
      "tov": 0,
      "pf": 1,
      "pts": 0,
      "plus_minus": -3.0,
      "adv_ts_pct": 0.0,
      "adv_efg_pct": 0.0,
      "adv_orb_pct": 0.0,
      "adv_drb_pct": 45.3,
      "adv_trb_pct": 24.5,
      "adv_ast_pct": 0.0,
      "adv_stl_pct": 17.8,
      "adv_blk_pct": 0.0,
      "adv_tov_pct": 0.0,
      "adv_usg_pct": 8.2,
      "adv_off_rtg": 0.0,
      "adv_def_rtg": 82.0,
      "adv_bpm": 4.5
    }
  ],
  "bref_id": "202211090MIN"
}