{
  "game_date": "2022-12-20",
  "home": "DEN",
  "visitor": "MEM",
  "home_pts": 105,
  "visitor_pts": 91,
  "home_starters": [
    "Kentavious Caldwell-Pope",
    "Nikola Joki\u00c4\u0087",
    "Bruce Brown",
    "Christian Braun",
    "Aaron Gordon"
  ],
  "visitor_starters": [
    "Ja Morant",
    "Steven Adams",
    "Dillon Brooks",
    "Jaren Jackson Jr.",
    "John Konchar"
  ],
  "players": [
    {
      "player_name": "Ja Morant",
      "team": "MEM",
      "is_home": false,
      "is_starter": true,
      "mp": 38.1,
      "fg": 12,
      "fga": 26,
      "fg_pct": 0.462,
      "fg3": 3,
      "fg3a": 6,
      "fg3_pct": 0.5,
      "ft": 8,
      "fta": 10,
      "ft_pct": 0.8,
      "orb": 0,
      "drb": 1,
      "trb": 1,
      "ast": 10,
      "stl": 0,
      "blk": 0,
      "tov": 7,
      "pf": 2,
      "pts": 35,
      "plus_minus": -16.0,
      "adv_ts_pct": 0.576,
      "adv_efg_pct": 0.519,
      "adv_orb_pct": 0.0,
      "adv_drb_pct": 2.6,
      "adv_trb_pct": 1.4,
      "adv_ast_pct": 60.4,
      "adv_stl_pct": 0.0,
      "adv_blk_pct": 0.0,
      "adv_tov_pct": 18.7,
      "adv_usg_pct": 44.4,
      "adv_off_rtg": 100.0,
      "adv_def_rtg": 115.0,
      "adv_bpm": 4.3
    },
    {
      "player_name": "Steven Adams",
      "team": "MEM",
      "is_home": false,
      "is_starter": true,
      "mp": 30.1,
      "fg": 2,
      "fga": 5,
      "fg_pct": 0.4,
      "fg3": 0,
      "fg3a": 0,
      "fg3_pct": null,
      "ft": 0,
      "fta": 0,
      "ft_pct": null,
      "orb": 4,
      "drb": 6,
      "trb": 10,
      "ast": 2,
      "stl": 1,
      "blk": 0,
      "tov": 2,
      "pf": 2,
      "pts": 4,
      "plus_minus": -8.0,
      "adv_ts_pct": 0.4,
      "adv_efg_pct": 0.4,
      "adv_orb_pct": 15.2,
      "adv_drb_pct": 19.9,
      "adv_trb_pct": 17.7,
      "adv_ast_pct": 9.7,
      "adv_stl_pct": 1.6,
      "adv_blk_pct": 0.0,
      "adv_tov_pct": 28.6,
      "adv_usg_pct": 10.5,
      "adv_off_rtg": 88.0,
      "adv_def_rtg": 106.0,
      "adv_bpm": -4.8
    },
    {
      "player_name": "Dillon Brooks",
      "team": "MEM",
      "is_home": false,
      "is_starter": true,
      "mp": 29.4,
      "fg": 5,
      "fga": 14,
      "fg_pct": 0.357,
      "fg3": 0,
      "fg3a": 5,
      "fg3_pct": 0.0,
      "ft": 1,
      "fta": 1,
      "ft_pct": 1.0,
      "orb": 0,
      "drb": 7,
      "trb": 7,
      "ast": 1,
      "stl": 3,
      "blk": 0,
      "tov": 1,
      "pf": 5,
      "pts": 11,
      "plus_minus": -21.0,
      "adv_ts_pct": 0.381,
      "adv_efg_pct": 0.357,
      "adv_orb_pct": 0.0,
      "adv_drb_pct": 23.8,
      "adv_trb_pct": 12.7,
      "adv_ast_pct": 5.9,
      "adv_stl_pct": 4.9,
      "adv_blk_pct": 0.0,
      "adv_tov_pct": 6.5,
      "adv_usg_pct": 23.7,
      "adv_off_rtg": 73.0,
      "adv_def_rtg": 97.0,
      "adv_bpm": -5.6
    },
    {
      "player_name": "Jaren Jackson Jr.",
      "team": "MEM",
      "is_home": false,
      "is_starter": true,
      "mp": 21.8,
      "fg": 3,
      "fga": 6,
      "fg_pct": 0.5,
      "fg3": 1,
      "fg3a": 3,
      "fg3_pct": 0.333,
      "ft": 1,
      "fta": 2,
      "ft_pct": 0.5,
      "orb": 0,
      "drb": 2,
      "trb": 2,
      "ast": 1,
      "stl": 3,
      "blk": 5,
      "tov": 1,
      "pf": 5,
      "pts": 8,
      "plus_minus": -13.0,
      "adv_ts_pct": 0.581,
      "adv_efg_pct": 0.583,
      "adv_orb_pct": 0.0,
      "adv_drb_pct": 9.2,
      "adv_trb_pct": 4.9,
      "adv_ast_pct": 7.5,
      "adv_stl_pct": 6.6,
      "adv_blk_pct": 17.8,
      "adv_tov_pct": 12.7,
      "adv_usg_pct": 16.4,
      "adv_off_rtg": 99.0,
      "adv_def_rtg": 86.0,
      "adv_bpm": 7.9
    },
    {
      "player_name": "John Konchar",
      "team": "MEM",
      "is_home": false,
      "is_starter": true,
      "mp": 15.6,
      "fg": 0,
      "fga": 1,
      "fg_pct": 0.0,
      "fg3": 0,
      "fg3a": 1,
      "fg3_pct": 0.0,
      "ft": 0,
      "fta": 0,
      "ft_pct": null,
      "orb": 0,
      "drb": 1,
      "trb": 1,
      "ast": 1,
      "stl": 0,
      "blk": 0,
      "tov": 0,
      "pf": 0,
      "pts": 0,
      "plus_minus": -14.0,
      "adv_ts_pct": 0.0,
      "adv_efg_pct": 0.0,
      "adv_orb_pct": 0.0,
      "adv_drb_pct": 6.4,
      "adv_trb_pct": 3.4,
      "adv_ast_pct": 8.6,
      "adv_stl_pct": 0.0,
      "adv_blk_pct": 0.0,
      "adv_tov_pct": 0.0,
      "adv_usg_pct": 2.9,
      "adv_off_rtg": 46.0,
      "adv_def_rtg": 114.0,
      "adv_bpm": -6.7
    },
    {
      "player_name": "Tyus Jones",
      "team": "MEM",
      "is_home": false,
      "is_starter": false,
      "mp": 29.9,
      "fg": 2,
      "fga": 6,
      "fg_pct": 0.333,
      "fg3": 0,
      "fg3a": 3,
      "fg3_pct": 0.0,
      "ft": 1,
      "fta": 1,
      "ft_pct": 1.0,
      "orb": 1,
      "drb": 4,
      "trb": 5,
      "ast": 4,
      "stl": 0,
      "blk": 0,
      "tov": 1,
      "pf": 0,
      "pts": 5,
      "plus_minus": -6.0,
      "adv_ts_pct": 0.388,
      "adv_efg_pct": 0.333,
      "adv_orb_pct": 3.8,
      "adv_drb_pct": 13.4,
      "adv_trb_pct": 8.9,
      "adv_ast_pct": 19.6,
      "adv_stl_pct": 0.0,
      "adv_blk_pct": 0.0,
      "adv_tov_pct": 13.4,
      "adv_usg_pct": 11.2,
      "adv_off_rtg": 92.0,
      "adv_def_rtg": 112.0,
      "adv_bpm": -7.0
    },
    {
      "player_name": "David Roddy",
      "team": "MEM",
      "is_home": false,
      "is_starter": false,
      "mp": 23.0,
      "fg": 3,
      "fga": 8,
      "fg_pct": 0.375,
      "fg3": 1,
      "fg3a": 5,
      "fg3_pct": 0.2,
      "ft": 1,
      "fta": 4,
      "ft_pct": 0.25,
      "orb": 0,
      "drb": 1,
      "trb": 1,
      "ast": 1,
      "stl": 3,
      "blk": 1,
      "tov": 1,
      "pf": 0,
      "pts": 8,
      "plus_minus": -2.0,
      "adv_ts_pct": 0.41,
      "adv_efg_pct": 0.438,
      "adv_orb_pct": 0.0,
      "adv_drb_pct": 4.4,
      "adv_trb_pct": 2.3,
      "adv_ast_pct": 7.0,
      "adv_stl_pct": 6.3,
      "adv_blk_pct": 3.4,
      "adv_tov_pct": 9.3,
      "adv_usg_pct": 21.2,
      "adv_off_rtg": 75.0,
      "adv_def_rtg": 100.0,
      "adv_bpm": 2.0
    },
    {
      "player_name": "Ziaire Williams",
      "team": "MEM",
      "is_home": false,
      "is_starter": false,
      "mp": 16.5,
      "fg": 1,
      "fga": 3,
      "fg_pct": 0.333,
      "fg3": 0,
      "fg3a": 2,
      "fg3_pct": 0.0,
      "ft": 0,
      "fta": 0,
      "ft_pct": null,
      "orb": 0,
      "drb": 4,
      "trb": 4,
      "ast": 4,
      "stl": 0,
      "blk": 0,
      "tov": 2,
      "pf": 1,
      "pts": 2,
      "plus_minus": 12.0,
      "adv_ts_pct": 0.333,
      "adv_efg_pct": 0.333,
      "adv_orb_pct": 0.0,
      "adv_drb_pct": 24.2,
      "adv_trb_pct": 12.9,
      "adv_ast_pct": 35.1,
      "adv_stl_pct": 0.0,
      "adv_blk_pct": 0.0,
      "adv_tov_pct": 40.0,
      "adv_usg_pct": 13.7,
      "adv_off_rtg": 68.0,
      "adv_def_rtg": 108.0,
      "adv_bpm": -4.8
    },
    {
      "player_name": "Brandon Clarke",
      "team": "MEM",
      "is_home": false,
      "is_starter": false,
      "mp": 16.1,
      "fg": 4,
      "fga": 7,
      "fg_pct": 0.571,
      "fg3": 0,
      "fg3a": 0,
      "fg3_pct": null,
      "ft": 2,
      "fta": 3,
      "ft_pct": 0.667,
      "orb": 2,
      "drb": 3,
      "trb": 5,
      "ast": 0,
      "stl": 0,
      "blk": 1,
      "tov": 0,
      "pf": 3,
      "pts": 10,
      "plus_minus": -10.0,
      "adv_ts_pct": 0.601,
      "adv_efg_pct": 0.571,
      "adv_orb_pct": 14.2,
      "adv_drb_pct": 18.7,
      "adv_trb_pct": 16.6,
      "adv_ast_pct": 0.0,
      "adv_stl_pct": 0.0,
      "adv_blk_pct": 4.8,
      "adv_tov_pct": 0.0,
      "adv_usg_pct": 23.4,
      "adv_off_rtg": 125.0,
      "adv_def_rtg": 106.0,
      "adv_bpm": 1.8
    },
    {
      "player_name": "Santi Aldama",
      "team": "MEM",
      "is_home": false,
      "is_starter": false,
      "mp": 14.1,
      "fg": 3,
      "fga": 4,
      "fg_pct": 0.75,
      "fg3": 0,
      "fg3a": 1,
      "fg3_pct": 0.0,
      "ft": 0,
      "fta": 0,
      "ft_pct": null,
      "orb": 0,
      "drb": 3,
      "trb": 3,
      "ast": 1,
      "stl": 1,
      "blk": 0,
      "tov": 1,
      "pf": 3,
      "pts": 6,
      "plus_minus": -4.0,
      "adv_ts_pct": 0.75,
      "adv_efg_pct": 0.75,
      "adv_orb_pct": 0.0,
      "adv_drb_pct": 21.4,
      "adv_trb_pct": 11.4,
      "adv_ast_pct": 13.3,
      "adv_stl_pct": 3.4,
      "adv_blk_pct": 0.0,
      "adv_tov_pct": 20.0,
      "adv_usg_pct": 16.1,
      "adv_off_rtg": 110.0,
      "adv_def_rtg": 101.0,
      "adv_bpm": 1.1
    },
    {
      "player_name": "Xavier Tillman Sr.",
      "team": "MEM",
      "is_home": false,
      "is_starter": false,
      "mp": 1.9,
      "fg": 1,
      "fga": 1,
      "fg_pct": 1.0,
      "fg3": 0,
      "fg3a": 0,
      "fg3_pct": null,
      "ft": 0,
      "fta": 0,
      "ft_pct": null,
      "orb": 0,
      "drb": 2,
      "trb": 2,
      "ast": 0,
      "stl": 0,
      "blk": 0,
      "tov": 0,
      "pf": 0,
      "pts": 2,
      "plus_minus": 4.0,
      "adv_ts_pct": 1.0,
      "adv_efg_pct": 1.0,
      "adv_orb_pct": 0.0,
      "adv_drb_pct": 100.0,
      "adv_trb_pct": 57.1,
      "adv_ast_pct": 0.0,
      "adv_stl_pct": 0.0,
      "adv_blk_pct": 0.0,
      "adv_tov_pct": 0.0,
      "adv_usg_pct": 24.2,
      "adv_off_rtg": 200.0,
      "adv_def_rtg": 82.0,
      "adv_bpm": 25.9
    },
    {
      "player_name": "Kennedy Chandler",
      "team": "MEM",
      "is_home": false,
      "is_starter": false,
      "mp": 1.9,
      "fg": 0,
      "fga": 0,
      "fg_pct": null,
      "fg3": 0,
      "fg3a": 0,
      "fg3_pct": null,
      "ft": 0,
      "fta": 0,
      "ft_pct": null,
      "orb": 0,
      "drb": 1,
      "trb": 1,
      "ast": 0,
      "stl": 0,
      "blk": 0,
      "tov": 0,
      "pf": 0,
      "pts": 0,
      "plus_minus": 4.0,
      "adv_ts_pct": null,
      "adv_efg_pct": null,
      "adv_orb_pct": 0.0,
      "adv_drb_pct": 53.6,
      "adv_trb_pct": 28.6,
      "adv_ast_pct": 0.0,
      "adv_stl_pct": 0.0,
      "adv_blk_pct": 0.0,
      "adv_tov_pct": null,
      "adv_usg_pct": 0.0,
      "adv_off_rtg": 0.0,
      "adv_def_rtg": 99.0,
      "adv_bpm": -6.3
    },
    {
      "player_name": "Jake LaRavia",
      "team": "MEM",
      "is_home": false,
      "is_starter": false,
      "mp": 1.9,
      "fg": 0,
      "fga": 0,
      "fg_pct": null,
      "fg3": 0,
      "fg3a": 0,
      "fg3_pct": null,
      "ft": 0,
      "fta": 0,
      "ft_pct": null,
      "orb": 0,
      "drb": 0,
      "trb": 0,
      "ast": 0,
      "stl": 0,
      "blk": 0,
      "tov": 0,
      "pf": 0,
      "pts": 0,
      "plus_minus": 4.0,
      "adv_ts_pct": null,
      "adv_efg_pct": null,
      "adv_orb_pct": 0.0,
      "adv_drb_pct": 0.0,
      "adv_trb_pct": 0.0,
      "adv_ast_pct": 0.0,
      "adv_stl_pct": 0.0,
      "adv_blk_pct": 0.0,
      "adv_tov_pct": null,
      "adv_usg_pct": 0.0,
      "adv_off_rtg": 0.0,
      "adv_def_rtg": 116.0,
      "adv_bpm": -7.1
    },
    {
      "player_name": "Kentavious Caldwell-Pope",
      "team": "DEN",
      "is_home": true,
      "is_starter": true,
      "mp": 37.6,
      "fg": 5,
      "fga": 11,
      "fg_pct": 0.455,
      "fg3": 2,
      "fg3a": 4,
      "fg3_pct": 0.5,
      "ft": 0,
      "fta": 0,
      "ft_pct": null,
      "orb": 0,
      "drb": 7,
      "trb": 7,
      "ast": 1,
      "stl": 1,
      "blk": 0,
      "tov": 3,
      "pf": 2,
      "pts": 12,
      "plus_minus": 17.0,
      "adv_ts_pct": 0.545,
      "adv_efg_pct": 0.545,
      "adv_orb_pct": 0.0,
      "adv_drb_pct": 21.2,
      "adv_trb_pct": 9.9,
      "adv_ast_pct": 3.8,
      "adv_stl_pct": 1.3,
      "adv_blk_pct": 0.0,
      "adv_tov_pct": 21.4,
      "adv_usg_pct": 15.3,
      "adv_off_rtg": 83.0,
      "adv_def_rtg": 94.0,
      "adv_bpm": -4.3
    },
    {
      "player_name": "Nikola Joki\u00c4\u0087",
      "team": "DEN",
      "is_home": true,
      "is_starter": true,
      "mp": 37.1,
      "fg": 6,
      "fga": 12,
      "fg_pct": 0.5,
      "fg3": 1,
      "fg3a": 1,
      "fg3_pct": 1.0,
      "ft": 0,
      "fta": 1,
      "ft_pct": 0.0,
      "orb": 4,
      "drb": 9,
      "trb": 13,
      "ast": 13,
      "stl": 2,
      "blk": 0,
      "tov": 4,
      "pf": 1,
      "pts": 13,
      "plus_minus": 13.0,
      "adv_ts_pct": 0.523,
      "adv_efg_pct": 0.542,
      "adv_orb_pct": 10.8,
      "adv_drb_pct": 27.7,
      "adv_trb_pct": 18.7,
      "adv_ast_pct": 52.2,
      "adv_stl_pct": 2.6,
      "adv_blk_pct": 0.0,
      "adv_tov_pct": 24.3,
      "adv_usg_pct": 18.2,
      "adv_off_rtg": 112.0,
      "adv_def_rtg": 90.0,
      "adv_bpm": 10.9
    },
    {
      "player_name": "Bruce Brown",
      "team": "DEN",
      "is_home": true,
      "is_starter": true,
      "mp": 35.4,
      "fg": 6,
      "fga": 15,
      "fg_pct": 0.4,
      "fg3": 1,
      "fg3a": 4,
      "fg3_pct": 0.25,
      "ft": 3,
      "fta": 3,
      "ft_pct": 1.0,
      "orb": 1,
      "drb": 4,
      "trb": 5,
      "ast": 4,
      "stl": 0,
      "blk": 2,
      "tov": 2,
      "pf": 4,
      "pts": 16,
      "plus_minus": 22.0,
      "adv_ts_pct": 0.49,
      "adv_efg_pct": 0.433,
      "adv_orb_pct": 2.8,
      "adv_drb_pct": 12.9,
      "adv_trb_pct": 7.5,
      "adv_ast_pct": 17.0,
      "adv_stl_pct": 0.0,
      "adv_blk_pct": 4.9,
      "adv_tov_pct": 10.9,
      "adv_usg_pct": 21.3,
      "adv_off_rtg": 102.0,
      "adv_def_rtg": 94.0,
      "adv_bpm": -0.4
    },
    {
      "player_name": "Christian Braun",
      "team": "DEN",
      "is_home": true,
      "is_starter": true,
      "mp": 28.9,
      "fg": 5,
      "fga": 11,
      "fg_pct": 0.455,
      "fg3": 2,
      "fg3a": 5,
      "fg3_pct": 0.4,
      "ft": 1,
      "fta": 2,
      "ft_pct": 0.5,
      "orb": 1,
      "drb": 2,
      "trb": 3,
      "ast": 1,
      "stl": 1,
      "blk": 1,
      "tov": 1,
      "pf": 3,
      "pts": 13,
      "plus_minus": 9.0,
      "adv_ts_pct": 0.547,
      "adv_efg_pct": 0.545,
      "adv_orb_pct": 3.5,
      "adv_drb_pct": 7.9,
      "adv_trb_pct": 5.5,
      "adv_ast_pct": 5.2,
      "adv_stl_pct": 1.7,
      "adv_blk_pct": 3.0,
      "adv_tov_pct": 7.8,
      "adv_usg_pct": 18.3,
      "adv_off_rtg": 106.0,
      "adv_def_rtg": 93.0,
      "adv_bpm": 1.4
    },
    {
      "player_name": "Aaron Gordon",
      "team": "DEN",
      "is_home": true,
      "is_starter": true,
      "mp": 27.5,
      "fg": 9,
      "fga": 16,
      "fg_pct": 0.563,
      "fg3": 1,
      "fg3a": 2,
      "fg3_pct": 0.5,
      "ft": 5,
      "fta": 7,
      "ft_pct": 0.714,
      "orb": 4,
      "drb": 3,
      "trb": 7,
      "ast": 4,
      "stl": 2,
      "blk": 1,
      "tov": 1,
      "pf": 0,
      "pts": 24,
      "plus_minus": 22.0,
      "adv_ts_pct": 0.629,
      "adv_efg_pct": 0.594,
      "adv_orb_pct": 14.5,
      "adv_drb_pct": 12.5,
      "adv_trb_pct": 13.6,
      "adv_ast_pct": 28.7,
      "adv_stl_pct": 3.5,
      "adv_blk_pct": 3.2,
      "adv_tov_pct": 5.0,
      "adv_usg_pct": 30.0,
      "adv_off_rtg": 133.0,
      "adv_def_rtg": 88.0,
      "adv_bpm": 18.8
    },
    {
      "player_name": "Jeff Green",
      "team": "DEN",
      "is_home": true,
      "is_starter": false,
      "mp": 24.1,
      "fg": 4,
      "fga": 7,
      "fg_pct": 0.571,
      "fg3": 0,
      "fg3a": 3,
      "fg3_pct": 0.0,
      "ft": 1,
      "fta": 6,
      "ft_pct": 0.167,
      "orb": 0,
      "drb": 2,
      "trb": 2,
      "ast": 1,
      "stl": 2,
      "blk": 1,
      "tov": 2,
      "pf": 2,
      "pts": 9,
      "plus_minus": 1.0,
      "adv_ts_pct": 0.467,
      "adv_efg_pct": 0.571,
      "adv_orb_pct": 0.0,
      "adv_drb_pct": 9.5,
      "adv_trb_pct": 4.4,
      "adv_ast_pct": 6.2,
      "adv_stl_pct": 4.0,
      "adv_blk_pct": 3.6,
      "adv_tov_pct": 17.2,
      "adv_usg_pct": 19.9,
      "adv_off_rtg": 75.0,
      "adv_def_rtg": 87.0,
      "adv_bpm": -1.9
    },
    {
      "player_name": "Vlatko \u00c4\u008can\u00c4\u008dar",
      "team": "DEN",
      "is_home": true,
      "is_starter": false,
      "mp": 20.0,
      "fg": 1,
      "fga": 1,
      "fg_pct": 1.0,
      "fg3": 1,
      "fg3a": 1,
      "fg3_pct": 1.0,
      "ft": 0,
      "fta": 0,
      "ft_pct": null,
      "orb": 2,
      "drb": 5,
      "trb": 7,
      "ast": 2,
      "stl": 0,
      "blk": 0,
      "tov": 3,
      "pf": 3,
      "pts": 3,
      "plus_minus": -4.0,
      "adv_ts_pct": 1.5,
      "adv_efg_pct": 1.5,
      "adv_orb_pct": 10.0,
      "adv_drb_pct": 28.6,
      "adv_trb_pct": 18.7,
      "adv_ast_pct": 12.8,
      "adv_stl_pct": 0.0,
      "adv_blk_pct": 0.0,
      "adv_tov_pct": 75.0,
      "adv_usg_pct": 8.2,
      "adv_off_rtg": 81.0,
      "adv_def_rtg": 95.0,
      "adv_bpm": -3.4
    },
    {
      "player_name": "Bones Hyland",
      "team": "DEN",
      "is_home": true,
      "is_starter": false,
      "mp": 15.2,
      "fg": 4,
      "fga": 15,
      "fg_pct": 0.267,
      "fg3": 2,
      "fg3a": 7,
      "fg3_pct": 0.286,
      "ft": 2,
      "fta": 2,
      "ft_pct": 1.0,
      "orb": 0,
      "drb": 1,
      "trb": 1,
      "ast": 1,
      "stl": 1,
      "blk": 0,
      "tov": 1,
      "pf": 3,
      "pts": 12,
      "plus_minus": -7.0,
      "adv_ts_pct": 0.378,
      "adv_efg_pct": 0.333,
      "adv_orb_pct": 0.0,
      "adv_drb_pct": 7.5,
      "adv_trb_pct": 3.5,
      "adv_ast_pct": 11.5,
      "adv_stl_pct": 3.2,
      "adv_blk_pct": 0.0,
      "adv_tov_pct": 5.9,
      "adv_usg_pct": 45.4,
      "adv_off_rtg": 80.0,
      "adv_def_rtg": 92.0,
      "adv_bpm": -8.0
    },
    {
      "player_name": "Zeke Nnaji",
      "team": "DEN",
      "is_home": true,
      "is_starter": false,
      "mp": 10.9,
      "fg": 0,
      "fga": 0,
      "fg_pct": null,
      "fg3": 0,
      "fg3a": 0,
      "fg3_pct": null,
      "ft": 3,
      "fta": 4,
      "ft_pct": 0.75,
      "orb": 1,
      "drb": 1,
      "trb": 2,
      "ast": 1,
      "stl": 0,
      "blk": 0,
      "tov": 0,
      "pf": 1,
      "pts": 3,
      "plus_minus": 1.0,
      "adv_ts_pct": 0.852,
      "adv_efg_pct": null,
      "adv_orb_pct": 9.2,
      "adv_drb_pct": 10.5,
      "adv_trb_pct": 9.8,
      "adv_ast_pct": 11.0,
      "adv_stl_pct": 0.0,
      "adv_blk_pct": 0.0,
      "adv_tov_pct": 0.0,
      "adv_usg_pct": 6.6,
      "adv_off_rtg": 195.0,
      "adv_def_rtg": 98.0,
      "adv_bpm": 3.8
    },
    {
      "player_name": "Davon Reed",
      "team": "DEN",
      "is_home": true,
      "is_starter": false,
      "mp": 1.6,
      "fg": 0,
      "fga": 0,
      "fg_pct": null,
      "fg3": 0,
      "fg3a": 0,
      "fg3_pct": null,
      "ft": 0,
      "fta": 0,
      "ft_pct": null,
      "orb": 0,
      "drb": 1,
      "trb": 1,
      "ast": 0,
      "stl": 0,
      "blk": 0,
      "tov": 0,
      "pf": 0,
      "pts": 0,
      "plus_minus": -2.0,
      "adv_ts_pct": null,
      "adv_efg_pct": null,
      "adv_orb_pct": 0.0,
      "adv_drb_pct": 70.0,
      "adv_trb_pct": 32.7,
      "adv_ast_pct": 0.0,
      "adv_stl_pct": 0.0,
      "adv_blk_pct": 0.0,
      "adv_tov_pct": null,
      "adv_usg_pct": 0.0,
      "adv_off_rtg": 0.0,
      "adv_def_rtg": 88.0,
      "adv_bpm": -0.6
    },
    {
      "player_name": "Ish Smith",
      "team": "DEN",
      "is_home": true,
      "is_starter": false,
      "mp": 1.6,
      "fg": 0,
      "fga": 1,
      "fg_pct": 0.0,
      "fg3": 0,
      "fg3a": 0,
      "fg3_pct": null,
      "ft": 0,
      "fta": 0,
      "ft_pct": null,
      "orb": 0,
      "drb": 0,
      "trb": 0,
      "ast": 0,
      "stl": 0,
      "blk": 0,
      "tov": 0,
      "pf": 0,
      "pts": 0,
      "plus_minus": -2.0,
      "adv_ts_pct": 0.0,
      "adv_efg_pct": 0.0,
      "adv_orb_pct": 0.0,
      "adv_drb_pct": 0.0,
      "adv_trb_pct": 0.0,
      "adv_ast_pct": 0.0,
      "adv_stl_pct": 0.0,
      "adv_blk_pct": 0.0,
      "adv_tov_pct": 0.0,
      "adv_usg_pct": 25.1,
      "adv_off_rtg": 0.0,
      "adv_def_rtg": 101.0,
      "adv_bpm": -29.1
    }
  ],
  "bref_id": "202212200DEN"
}